superfancy/__init__.py
superfancy/ansi.py
superfancy/background.py
superfancy/color.py
superfancy/style.py
superfancy-1.0.1.dist-info/LICENSE
superfancy-1.0.1.dist-info/LICENSE.Apache-2.0
superfancy-1.0.1.dist-info/METADATA
superfancy-1.0.1.dist-info/WHEEL
superfancy-1.0.1.dist-info/top_level.txt
superfancy-1.0.1.dist-info/RECORD
